[
    {
      "name": "安達與島村",
      "date": "10/00",
      "time": "00:00",
      "carrier": "Novel",
      "season": 1,
      "nameInJpn": "安達としまむら",
      "img": "https://cdn.discordapp.com/attachments/439314137584107532/721423983714762792/keyvisual_2_new2.png",
      "official": "https://www.tbs.co.jp/anime/adashima/",
      "description": "女高中生安達與島村，在體育館二樓相遇便成為了朋友。兩人聊喜歡的電視節目或料理，偶爾打打桌球，培育名為友情的情感。在這之中，安達對島村抱持著特別的情感，安達對於自己心中萌生出的特殊情感相當苦惱，過著普通高中生活的安達與島村彼此的關係稍微改變。"
    },
    {
      "name": "進擊的巨人 The Final Season",
      "date": "10/00",
      "time": "00:00",
      "carrier": "Comic",
      "season": 4,
      "nameInJpn": "進撃の巨人 The Final Season",
      "img": "https://cdn.discordapp.com/attachments/439314137584107532/728232530859524206/visual_01.png",
      "official": "http://shingeki.net/",
      "description": "《進擊的巨人》故事描述百年前世界莫名出現神秘的巨人怪物，不斷殘忍食人，人類幾乎無法與之對抗，最後人類建造了三道寬 3 公尺、高 50 公尺的高聳圍牆，百年來未有巨人攻破，10 歲的艾連，親眼見到母親被巨人一口咬碎的慘劇，艾連發誓要消滅所有巨人。"
    },
    {
      "name": "勇者鬥惡龍 達伊的大冒險",
      "date": "10/00",
      "time": "00:00",
      "carrier": "Comic",
      "season": 1,
      "nameInJpn": "ドラゴンクエスト ダイの大冒険",
      "img": "https://cdn.discordapp.com/attachments/439314137584107532/728233565082615828/ogp.png",
      "official": "https://dq-dai.com/",
      "description": "魔王巴特拉被勇者阿邦（艾班）擊敗後，世界回復了和平。一班跟隨魔王的怪物回復善良，並到伶仃島（台版漫畫：迪魯木靈島，台版動畫：戴爾馬林島）生活。及後一名嬰孩飄流到島上，並被一魔怪收養；該魔怪為嬰孩取名為「小呆」，而小呆也一直稱收養他的魔怪為爺爺。"
    },
    {
      "name": "給不滅的你",
      "date": "10/00",
      "time": "00:00",
      "carrier": "Comic",
      "season": 1,
      "nameInJpn": "不滅のあなたへ",
      "img": "https://cdn.discordapp.com/attachments/439314137584107532/728234230336716820/maxresdefault.png",
      "official": "https://anime-fumetsunoanatae.com/",
      "description": "作品故事描述，某人把「球」放進這片土地。具備收集情報的機能，還可以變換各種外貌，那個球體甚至連死亡都能超越。某天，它遇見了少年，之後又分開。光線、味道、聲音、溫度、痛苦、喜悅、哀傷...在這個充滿刺激的世界裡徘徊，展開一段永恆之旅。"
    },
    {
      "name": "我立於百萬生命之上",
      "date": "10/00",
      "time": "00:00",
      "carrier": "Comic",
      "season": 1,
      "nameInJpn": "100万の命の上に俺は立っている",
      "img": "https://cdn.discordapp.com/attachments/439314137584107532/728234949722767410/maxresdefault.png",
      "official": "http://1000000-lives.com/",
      "description": "中學三年級的四谷友助總是特立獨行，沒有參加社團，不交朋友，喜歡獨自行動。某天放學後，四谷突然被捲進了異世界，在那裡遇見的竟是兩位同班的女同學──新堂衣宇和箱崎紅末，新堂是品學兼優、外表亮麗的班上風雲人物，箱崎則是體弱多病、存在感薄弱的女生。接下來，三人的冒險就此展開...不過在那之前，卻冒出了只有半張臉的人..."
    },
    {
      "name": "總之就是很可愛",
      "date": "10/00",
      "time": "00:00",
      "carrier": "Comic",
      "season": 1,
      "nameInJpn": "トニカクカワイイ",
      "img": "https://cdn.discordapp.com/attachments/439314137584107532/728236409185370112/unknown.png",
      "official": "http://tonikawa.com/",
      "description": "學業優秀、正在備考高中入學考試的由崎星空，在一個雪夜中偶遇在街對面小憩的少女月讀司，並對她一見鍾情。正當星空跨過街道打算向司搭訕時，迎面卻駛來了一輛卡車。幸得司捨身相救，星空得以保住性命，但司卻沒有留下名字便轉頭離去。害怕司會像輝夜姬一樣就此和自己永別的星空，不顧身上的重傷起身奮力追趕司，並對其告白。司告訴星空「如果你願意和我結婚，那我就跟你交往」，星空當即應承，隨後昏倒在地。"
    },
    {
      "name": "黃金神威",
      "nameInJpn": "ゴールデンカムイ 第三期",
      "date": "10/8",
      "time": "23:00",
      "carrier": "Comic",
      "season": "3",
      "img": "https://i.imgur.com/CuoOdFB.jpg",
      "official": "http://www.kamuy-anime.com/",
      "description": "生存、尋寶，為了黃金的戰鬥在神秘的古北海道大地正式展開—— 被稱為『不死身的杉元』、在日俄戰爭中有如鬼神般的殺敵，被世人如此熟知的杉元佐一，為了得到大量的黃金，來到了昔日淘金熱潮盛行的北海道。於某次機遇下，他得知了隱藏著阿伊努人龐大財寶的線索！？在充滿威嚴的大自然中，和許多兇惡的死刑犯、以及阿伊努少女相遇，『尋找黃金的生存競爭』正式開幕！！！"
  },
    {
      "name": "請問您今天要來點兔子嗎？BLOOM",
      "date": "10/00",
      "time": "00:00",
      "carrier": "Comic",
      "season": 3,
      "nameInJpn": "ご注文はうさぎですか? BLOOM",
      "img": "https://cdn.discordapp.com/attachments/439314137584107532/728237143356604547/main_img.png",
      "official": "https://gochiusa.com/bloom/",
      "description": "「兔子～兔子～」天真地邊這麼唱著歌，邊為了高中入學尋找著寄宿地點而迷路的心愛，意外發現了一間名叫“Rabbit House”的咖啡店。當心愛一邊喝著咖啡，一邊詢問地點時，才發現原來這裡就是自己正在尋找的寄宿之家。由於心愛就讀的高中規定，必須幫忙寄宿的家庭工作以當作借住的報答。"
    },
    {
      "name": "狗和貓一起養，每天都很快樂",
      "date": "10/00",
      "time": "00:00",
      "carrier": "Comic",
      "season": 1,
      "nameInJpn": "犬と猫どっちも飼ってると毎日たのしい",
      "img": "https://cdn.discordapp.com/attachments/439314137584107532/728238984332968057/output.webp",
      "official": "https://dog-and-cat.com/",
      "description": "一生懸命でかわいすぎる犬と、恐すぎる顔なのに憎めない猫と。二匹と暮らす楽しすぎる日常――。どっちも飼っている飼い主ならではの毎日は、笑いありホロリあり…。あなたは犬派？猫派？どっちも派？？犬も猫もかわいくて仕方ない欲張りな飼い主が贈る贅沢などっちも飼いアニメがはじまります。"
    },
    {
      "name": "A3！ SEASON AUTUMN & WINTER",
      "date": "10/00",
      "time": "00:00",
      "carrier": "Game",
      "season": 1,
      "nameInJpn": "A3! SEASON AUTUMN & WINTER",
      "img": "https://cdn.discordapp.com/attachments/439314137584107532/728241570629025874/mainimg_autumn.png",
      "official": "https://www.a3-animation.jp/",
      "description": "是以培養24位元劇團的團員為主題的養成遊戲，玩家在遊戲中扮演前演員立花泉，身負重振劇團榮光的重責大任，最終帶領團員進行公演。"
    },
    {
      "name": "比方說，這是個出身魔王關附近的少年在新手村生活的故事",
      "date": "10/00",
      "time": "00:00",
      "carrier": "Novel",
      "season": 1,
      "nameInJpn": "たとえばラストダンジョン前の村の少年が序盤の街で暮らすような物語",
      "img": "https://cdn.discordapp.com/attachments/439314137584107532/728242604495601704/unknown.png",
      "official": "https://lasdan.com/",
      "description": "儘管受到村裡眾人反對，少年羅伊德還是無法放棄參軍的夢想，啟程前往王都。然而，包含被說是村裡最弱的他在內，竟然沒有任何村人知道他們的村子被稱為「最終地下城旁邊的怪物魔境」這個事實，連高等級的冒險者也聞之膽寒。"
    },
    {
      "name": "第501統合戰鬥航空團 強襲魔女 ROAD to BERLIN",
      "date": "10/00",
      "time": "00:00",
      "carrier": "Comic",
      "season": 1,
      "nameInJpn": "第501統合戦闘航空団 ストライクウィッチーズ ROAD to BERLIN",
      "img": "https://cdn.discordapp.com/attachments/439314137584107532/728243378537627648/vPw56J5.png",
      "official": "http://w-witch.jp/s-witch/pc/",
      "description": "動畫《強襲魔女 通往柏林之路》是強襲魔女系列新作，2020年播出。"
    },
    {
      "name": "眾神眷顧的男人",
      "date": "10/00",
      "time": "00:00",
      "carrier": "Novel",
      "season": 1,
      "nameInJpn": "神達に拾われた男",
      "img": "https://cdn.discordapp.com/attachments/439314137584107532/728244040386084985/kv_pc.png",
      "official": "https://kamihiro-anime.com/",
      "description": "在眾神的眷顧之下，帶著史萊姆一起展開悠閒的異世界生活！竹林龍馬是日本的中年上班族，他的一生在疾病中劃下句點。雖然是人生失敗組，然而龍馬在死後卻應三大神之邀，以小孩子的身分轉生至劍與魔法的異世界！受到眾神眷顧的龍馬，獨自在森林中過著悠遊自得的生活。專注於魔法以及狩獵的期間，龍馬最感興趣的工作居然是研究受他使役的史萊姆！帶領各式各樣的史萊姆（包括新品種），與正直善良的鄉民來往，歌頌自己的第二人生。異世界慢活幻想物語，正式揭開序幕！"
    },
    {
      "name": "KING'S RAID 繼承意志的人們",
      "date": "10/00",
      "time": "00:00",
      "carrier": "Game",
      "season": 1,
      "nameInJpn": "キングスレイド 意志を継ぐものたち",
      "img": "https://cdn.discordapp.com/attachments/439314137584107532/728244759755358288/89bb986.png",
      "official": "https://www.anime-kings-raid.com/",
      "description": "光の女神<ルア>が創造した世界の半分以上を占める広大なオルビス大陸は、人間のみならず様々な種族が暮らしている種族のるつぼである。本作の舞台は<オルベリア王国>。オルベリア王国は100年前、魔界より現れた魔王<アングムンド>の侵攻に端を発する戦争において、聖剣エアとともに破竹の活躍をみせた国王カイルを輩出した国である。カイルは各種族の仲間とともに魔王軍に抵抗。ついにはアングムンドを退けるものの、自身も決戦の最中に生死不明となる。"
    },
    {
      "name": "半妖的夜叉姬",
      "date": "10/00",
      "time": "00:00",
      "carrier": "Comic",
      "season": 1,
      "nameInJpn": "半妖の夜叉姫",
      "img": "https://cdn.discordapp.com/attachments/439314137584107532/728246262662692945/keyv_pc02.png",
      "official": "http://hanyo-yashahime.com/",
      "description": "內容為《犬夜叉》的續作，描述殺生丸的女兒永久、剎那，還有犬夜叉與阿籬的女兒諸刃（暫譯）三人一起冒險的故事。"
    },
    {
      "name": "成為神的那天",
      "date": "10/00",
      "time": "00:00",
      "carrier": "Original",
      "season": 1,
      "nameInJpn": "神様になった日",
      "img": "https://cdn.discordapp.com/attachments/439314137584107532/728248543298715648/img_naga.png",
      "official": "https://kamisama-day.jp/",
      "description": "作為神而覺醒的少女·雛預見了“世界的終結”。於是她選擇了一位少年。在終結到來之前，作為見證者——"
    },
    {
      "name": "咒術迴戰",
      "date": "10/00",
      "time": "00:00",
      "carrier": "Comic",
      "season": 1,
      "nameInJpn": "呪術廻戦",
      "img": "https://cdn.discordapp.com/attachments/439314137584107532/728247975020855296/unknown.png",
      "official": "https://jujutsukaisen.jp/",
      "description": "人類的負面情緒累積混雜後會形成咒靈並對人類造成危害，只有使用被稱為咒力的能量才得以祓除，而負責祓除的人稱為咒術師。日本有兩間咒術教育機構，分別位於東京和京都的咒術高等專門學校。咒物是帶有強大咒力的物品，通常因難以破壞而被咒術高專保管，若經過妥善封印，可以辟邪。"
    },
    {
      "name": "熊熊勇闖異世界",
      "date": "10/00",
      "time": "00:00",
      "carrier": "Novel",
      "season": 1,
      "nameInJpn": "くまクマ熊ベアー",
      "img": "https://cdn.discordapp.com/attachments/439314137584107532/728248877244874822/main_img_2.png",
      "official": "https://kumakumakumabear.com/",
      "description": "家裡蹲的優奈在遊戲中抽獎，獲得了獎品「熊熊裝備」和「穿越到異世界」。結果優奈就在異世界中穿著熊熊裝備，打倒怪物，幫助小女孩，保護村莊。最強熊熊冒險者勇闖異世界。"
    },
    {
      "name": "魔法科高中的劣等生 來訪者篇",
      "date": "10/00",
      "time": "00:00",
      "carrier": "Novel",
      "season": 2,
      "nameInJpn": "魔法科高校の劣等生 来訪者編",
      "img": "https://cdn.discordapp.com/attachments/439314137584107532/728250265932922960/kv_min.png",
      "official": "https://mahouka.jp/",
      "description": "故事敘述進入國立魔法大學附屬第一高中就讀的兄妹司波達也與司波深雪，在保持與四葉家關係秘密的同時，嘗試過著平安的日常生活。司波達也因無能而招人迴避，而司波深雪則因魔法功能而備受驗證。"
    },
    {
      "name": "催眠麥克風",
      "date": "10/00",
      "time": "00:00",
      "carrier": "Original",
      "season": 1,
      "nameInJpn": "ヒプノシスマイク-Division Rap Battle-",
      "img": "https://cdn.discordapp.com/attachments/439314137584107532/728251481182175362/pc_visual12.png",
      "official": "https://hypnosismic.com/",
      "description": "H歷，使用武力的戰爭已經滅絕... 糾紛不是以槍支解決而是干涉人的精神的方式進行。一種名為「催眠麥克風」的特殊的麥克風出現。 「催眠麥克風」的歌詞會通過刺激人的交叉神經和副交感神經。使人體達到各種不同的狀態。 人們用Rap來決定勝負。男性生活在「中王區」之外的六個DIVISION中: 「池袋」、「橫濱」、「澀谷」、「新宿」、「名古屋」和「大阪」。 每個DIVISION的代表MC戰鬥之後，勝者可以獲得其他區域的部分領土。 不是兵器， 而是用語言為力量的世界。他們賭上自己的威信，開始了領土之間的對戰。"
    },
    {
      "name": "惡玉Drive",
      "date": "10/00",
      "time": "00:00",
      "carrier": "Original",
      "season": 1,
      "nameInJpn": "アクダマドライブ",
      "img": "https://cdn.discordapp.com/attachments/439314137584107532/728252088466931732/kv1.png",
      "official": "https://akudama-drive.com/",
      "description": "本作以「惡人們貫徹自我生存方式的物語」為主題，在高度發展卻扭曲的社會中，政治與警力衰退，被稱為「惡玉（アクダマ）」的犯罪者橫行，他們為了保持最符合自己風格的生活，彼此互相較勁自己的犯罪美學。"
    },
    {
      "name": "前說！",
      "date": "10/00",
      "time": "00:00",
      "carrier": "Novel",
      "season": 1,
      "nameInJpn": "まえせつ!",
      "img": "https://cdn.discordapp.com/attachments/439314137584107532/728256358155157554/kv3.png",
      "official": "https://maesetsu.jp/",
      "description": "《前說！》是由Studio五組和AXsiZ共同製作的日本原創電視動畫"
    },
    {
      "name": "EX-ARM",
      "date": "10/00",
      "time": "00:00",
      "carrier": "Comic",
      "season": 1,
      "nameInJpn": "EX-ARM エクスアーム",
      "img": "https://cdn.discordapp.com/attachments/439314137584107532/728257052320727070/unknown.png",
      "official": "https://www.exarm-anime.com/",
      "description": "描述因為在 2014 年遭逢交通意外而將大腦取出、再次醒來之後已經是 2030 年的少年夏目 AKIRA，發現自己已經成為名為「EX-ARM“No.00-α”」的兵器。擁有超強能力的他，為了找回失去的記憶而協助警察內部組織 EX-ARM 對策課展開打擊罪犯的活動。"
    },
    {
      "name": "Assault Lily Bouquet",
      "date": "10/00",
      "time": "00:00",
      "carrier": "Original",
      "season": 1,
      "nameInJpn": "アサルトリリィ Bouquet",
      "img": "https://cdn.discordapp.com/attachments/439314137584107532/728258277938561056/E382ADE383BCE38393E382B8E383A5E382A2E383AB.png",
      "official": "https://anime.assaultlily-pj.com/",
      "description": "名為「HUGE」的巨大生命體出現在近未來的地球，人類面臨毀滅的危機。於是人們開發了名為「CHARM」的決戰兵器。CHARM對於十幾歲的女性顯現出高同步率，而能夠操縱CHARM的女性被稱作「LILY」並逐漸被視為英雄。為了對抗HUGE而成立的LILY養成機構「GARDEN」設立於世界各地。這是在這些GARDEN當中，以成為出色的LILY為目標而戰的少女們的故事。"
    },
    {
      "name": "在地下城尋求邂逅是否搞錯了什麼III",
      "date": "10/00",
      "time": "00:00",
      "carrier": "Novel",
      "season": 3,
      "nameInJpn": "ダンジョンに出会いを求めるのは間違っているだろうかIII",
      "img": "https://cdn.discordapp.com/attachments/439314137584107532/728258898301026465/mainImg.png",
      "official": "http://danmachi.com/danmachi3/",
      "description": "故事描述「地下城」名為未知的興奮、光輝顯赫的榮耀、以及相遇可愛女生的浪漫，在這人們的夢想與欲望交集的城市裡，以冒險者為志願的少年貝爾遇見了成員為 0 人的神明大人赫斯緹雅，由少年踏出、女神記敘的「眷族物語」的冒險即將展開。"
    },
    {
      "name": "月歌。THE ANIMATION2",
      "date": "10/00",
      "time": "00:00",
      "carrier": "Original",
      "season": 1,
      "nameInJpn": "ツキウタ。THE ANIMATION2",
      "img": "https://cdn.discordapp.com/attachments/439314137584107532/728259696921673819/unknown.png",
      "official": "https://tsukiani.com/",
      "description": "月野藝能事務所旗下的兩組偶像團體―Six Gravity（通稱：Gravi）與Procellarum（通稱：Procella），是互相競爭的兄弟團體。他們住在東京都內的月野宿舍，共同生活著，並以新人偶像之姿互相競爭、切磋奮鬥著！男孩們努力進行偶像活動時的閃耀姿態，以及平凡日常生活中的真實樣貌，都在此呈現。——Gravi 與 Procella 的偶像日常故事，即將開始。"
    },
    {
      "name": "戰翼的希格德莉法",
      "date": "10/00",
      "time": "00:00",
      "carrier": "Original",
      "season": 1,
      "nameInJpn": "戦翼のシグルドリーヴァ",
      "img": "https://cdn.discordapp.com/attachments/439314137584107532/728261272344330400/unknown.png",
      "official": "https://sigururi.com/",
      "description": "突然出現在地球造成威脅的「ピラー」，此時對於被逼入絕境的人類伸出援手的，是自稱為「奧丁」的神，奧丁賜予了人類女武神「瓦爾基里」及能夠成為她們翅膀的英靈機，展開反擊。多年過後，持續進行戰爭的空中，有著女武神們還有支持著她們的男性們。此時的日本，佇立在富士山的強大對手，三名女武神與來自歐洲的飛行員，將如何對抗……。"
    },
    {
      "name": "滿溢的水果塔",
      "date": "10/00",
      "time": "00:00",
      "carrier": "Comic",
      "season": 1,
      "nameInJpn": "おちこぼれフルーツタルト",
      "img": "https://cdn.discordapp.com/attachments/439314137584107532/728262251282432130/unknown.png",
      "official": "http://ochifuru-anime.com/",
      "description": "憧憬著成為偶像而來到東京的高中一年級女孩櫻衣乃，搬進了小白鼠製作公司第4宿舍，通稱「老鼠莊」，卻在這裡得知了宿舍即將被拆除的消息。為了阻止老鼠莊被拆除，衣乃與老鼠莊的其他成員決定挑戰經紀人的企劃「滿溢的水果塔」而一同組成了偶像團體「水果塔」。"
    },
    {
      "name": "池袋西口公園",
      "date": "10/00",
      "time": "00:00",
      "carrier": "Novel",
      "season": 1,
      "nameInJpn": "池袋ウエストゲートパーク",
      "img": "https://cdn.discordapp.com/attachments/439314137584107532/728262773607497818/mv.png",
      "official": "https://iwgp-anime.com/",
      "description": "池袋西口公園一帶出現了變態殺人狂，連續有年輕貌美的女孩被殘忍殺害。小頭目組織頭領的真島誠（長瀨智也飾）不幸被當作了嫌疑犯，為了能證實自己的清白，誠和自己的兄弟G-boys首領安藤崇（窪塚洋介飾）、水野俊（山下智久飾）等人在池袋公園到處查找真兇。"
    },
    {
      "name": "無能力者娜娜",
      "date": "10/00",
      "time": "00:00",
      "carrier": "Comic",
      "season": 1,
      "nameInJpn": "無能なナナ",
      "img": "https://cdn.discordapp.com/attachments/439314137584107532/730755300222566450/vis.png",
      "official": "https://munounanana.com/",
      "description": "以一座環海孤島上的學園作為舞台，為了將人類的敵人趕盡殺絕，這裡訓練著有能力的年輕人們，而帶著抹殺掉能力者的心情轉入學校的少女「柊奈奈（柊ナナ）」，將與其他學生們展開一場又一場智謀的對戰。"
    },
    {
      "name": "憂國的莫里亞蒂",
      "date": "10/00",
      "time": "00:00",
      "carrier": "Comic",
      "season": 1,
      "nameInJpn": "憂国のモリアーティ",
      "img": "https://cdn.discordapp.com/attachments/439314137584107532/732935803226947654/unknown.png",
      "official": "https://moriarty-anime.com/",
      "description": "《憂國的莫里亞蒂》以小說家柯南道爾所著之推理小說系列《夏洛克福爾摩斯》為基礎，描繪站在與福爾摩斯對立立場的莫里亞蒂教授，以他為出發點，帶讀者了解不同觀點的另一面。"
    },
    {
      "name": "魔女之旅",
      "date": "10/00",
      "time": "00:00",
      "carrier": "Novel",
      "season": 1,
      "nameInJpn": "魔女の旅々",
      "img": "https://cdn.discordapp.com/attachments/439314137584107532/732937057055539240/unknown.png",
      "official": "https://majotabi.jp/",
      "description": "「請別在意。我是旅人，得繼續旅行才行。」某個地方有個正在旅行的魔女，她的名字是伊蕾娜。身為旅人，在很長很長的旅途中，她與形形色色的國家與人們邂逅。只允許魔法師入境的國家、最喜歡肌肉的壯漢、在死亡深淵等待戀人歸來的青年、獨自留守國家早已滅亡的公主，最後，還有她身為魔女的至今為止與從今以後。"
    },
    {
      "name": "小松先生",
      "date": "10/00",
      "time": "00:00",
      "carrier": "Comic",
      "season": 3,
      "nameInJpn": "おそ松さん",
      "img": "https://cdn.discordapp.com/attachments/439314137584107532/732939201393197116/img_main.png",
      "official": "https://osomatsusan.com/",
      "description": "松野家的六胞胎是本作的主角，身高、長相、外型大致相同。為了讓觀眾易於分辨，製作組使用了代表色作區別，並替角色增添了許多個人特點。六人的年齡皆為20多歲，生日5月24日，血型A型。所有人都喜歡魚魚子。全員無業，皆為啃老族、處男。 "
    },
    {
      "name": "暮蟬悲鳴時",
      "date": "10/00",
      "time": "00:00",
      "carrier": "Game",
      "season": 2,
      "nameInJpn": "ひぐらしのなく頃に",
      "img": "https://cdn.discordapp.com/attachments/439314137584107532/732939710887886958/v_001.png",
      "official": "https://higurashianime.com/",
      "description": "本作品為以昭和50年代之虛構村莊「雛見澤」（雛見沢，ひなみざわ）村為舞台，並以該村之古老習俗「綿流し」（わたながし）為軸所引起的一連串連續死亡事件。作品中以平行的次元輪迴的形式，來諷刺人類深層充滿罪惡的本性，並在結局中指出只有團結一心才可以克服。"
    },
    {
      "name": "排球少年！！ TO THE TOP",
      "nameInJpn": "ハイキュー!! TO THE TOP",
      "date": "1/10",
      "time": "25:25",
      "carrier": "Comic",
      "season": 4,
      "episode": "25",
      "img": "https://cdn.discordapp.com/attachments/668476222287642625/668478208810680331/volley.jpg",
      "official": "https://haikyu.jp/",
      "description": "春季的高中排球宮城縣預選中，在一番激鬥後取勝，終於實現在全國大賽中出場這一夙願的烏野高中排球部。 就在他們為全國大賽做準備的時候，傳來了影山受到全日本青年強化合宿召集的消息。而月島也受到宮城縣一年級選拔強化合宿的召集。 同為一年級，對於差距感到不安的日向，擅自前去參加宮城縣一年級選拔強化合宿，但……！ ？以全國大賽正賽為目標，日向、影山以及烏野高中排球部開始了更加艱鉅的挑戰 ——！ ！"
    },
    {
      "name": "這是妳與我的最後戰場，或是開創世界的聖戰",
      "date": "10/00",
      "time": "00:00",
      "carrier": "Novel",
      "season": 1,
      "nameInJpn": "キミと僕の最後の戦場、あるいは世界が始まる聖戦",
      "img": "https://cdn.discordapp.com/attachments/439314137584107532/732942817445281792/unknown.png",
      "official": "https://kimisentv.com/",
      "description": "坐擁強大科學力量的帝國，以及以「魔女之國」的威名受到世人畏懼的涅比利斯皇廳。在沒有盡頭的兩國戰場上，少年與少女相遇了。以史上最低齡晉升帝國最強戰力的劍士──伊思卡。被稱為皇廳最強的寒冰魔女公主──愛麗絲莉潔。兩人以宿敵的身分展開了廝殺。然而，少年被少女的美貌和高潔的姿態奪走了心，少女也迷上了少年的強大和生存之道。即便兩人無法並肩而行，唯能戰至一方倒下──相互敵對的少年少女，將展開革新世界的英雄傳奇！"
    },
    {
      "name": "在魔王城說晚安",
      "date": "10/00",
      "time": "00:00",
      "carrier": "Comic",
      "season": 1,
      "nameInJpn": "魔王城でおやすみ",
      "img": "https://cdn.discordapp.com/attachments/439314137584107532/741878491200487524/visual_02.png",
      "official": "https://maoujo-anime.com/",
      "description": "以被魔王抓走公主的奇幻故事作背景，以公主在魔王城中尋求安眠為主題，當中橫插王道故事情節的搞笑短篇故事。"
    },
    {
      "name": "小碧藍幻想！",
      "nameInJpn": "ぐらぶるっ!",
      "date": "10/00",
      "time": "00:00",
      "carrier": "Comic",
      "season": 1,
      "img": "https://cdn.discordapp.com/attachments/468412959119638550/627456015390212109/D1OCbLzU4AANr7w.png",
      "official": "https://guraburu.granbluefantasy.jp/",
      "description": ""
    },
    {
      "carrier": "Novel",
      "date": "10/00",
      "description": "",
      "img": "https://cdn.discordapp.com/attachments/439314137584107532/741880482081538058/mainvisual.png",
      "name": "攀岩！ -Climbing Girls-",
      "nameInJpn": "いわかける! -Climbing Girls-",
      "official": "http://iwakakeru-anime.com/",
      "season": 1,
      "time": "00:00"
    }
]